staaax/__init__.py
staaax/angled_stratified.py
staaax/angled_stratified_treams.py
staaax/fresnel.py
staaax/propagation.py
staaax/tildify.py
staaax-1.0.0.dist-info/METADATA
staaax-1.0.0.dist-info/WHEEL
staaax-1.0.0.dist-info/top_level.txt
staaax-1.0.0.dist-info/RECORD
