Metadata-Version: 2.4
Name: staaax
Version: 1.0.0
Summary: Jax based S-matrix stack solver.
Requires-Python: >=3.11
Requires-Dist: diffaaable>=1.0.1
Requires-Dist: matplotlib>=3.9.2
Requires-Dist: sax>=0.14.1
Requires-Dist: scipy>=1.14.1
Requires-Dist: treams>=0.4.5
